nlp_code_1/__init__.py
nlp_code_1/nlp_code_123.py
nlp_code_1-0.9.dist-info/METADATA
nlp_code_1-0.9.dist-info/WHEEL
nlp_code_1-0.9.dist-info/top_level.txt
nlp_code_1-0.9.dist-info/RECORD
