Metadata-Version: 2.1
Name: nlp-code-1
Version: 0.9
Summary: code
Author: Your Name
Requires-Python: >=3.6
